{"mean":{"confidence_interval":{"confidence_level":0.95,"lower_bound":40057210875.6625,"upper_bound":40143949086.48},"point_estimate":40100156434.3,"standard_error":22202910.109468177},"median":{"confidence_interval":{"confidence_level":0.95,"lower_bound":40044189565.0,"upper_bound":40166930221.0},"point_estimate":40089403532.0,"standard_error":30034642.381068785},"median_abs_dev":{"confidence_interval":{"confidence_level":0.95,"lower_bound":15414181.24614358,"upper_bound":129865103.73083353},"point_estimate":81399304.22157347,"standard_error":29356050.285178997},"slope":null,"std_dev":{"confidence_interval":{"confidence_level":0.95,"lower_bound":41455695.06307973,"upper_bound":94385058.11328076},"point_estimate":74040069.62968619,"standard_error":13555982.138021559}}